inventree_template_editor/__init__.py
inventree_template_editor/core.py
inventree_template_editor/static/labelEditor.dev.js
inventree_template_editor/static/dist/labelEditor.js
inventree_template_editor_plugin-0.2.1.dist-info/licenses/LICENSE
inventree_template_editor_plugin-0.2.1.dist-info/METADATA
inventree_template_editor_plugin-0.2.1.dist-info/WHEEL
inventree_template_editor_plugin-0.2.1.dist-info/entry_points.txt
inventree_template_editor_plugin-0.2.1.dist-info/top_level.txt
inventree_template_editor_plugin-0.2.1.dist-info/RECORD
