Metadata-Version: 2.4
Name: inventree-template-editor-plugin
Version: 0.2.1
Summary: A visual editor to build InvenTree label templates.
Author-email: wolflu05 <76838159+wolflu05@users.noreply.github.com>
License-Expression: GPL-3.0+
Project-URL: Homepage, https://github.com/wolflu05/inventree-template-editor-plugin
Keywords: inventree,plugin
Classifier: Programming Language :: Python :: 3
Classifier: Operating System :: OS Independent
Classifier: Framework :: InvenTree
Requires-Python: >=3.9
License-File: LICENSE
Dynamic: license-file
